luangpor/__init__.py
luangpor-0.0.3.dist-info/LICENSE
luangpor-0.0.3.dist-info/METADATA
luangpor-0.0.3.dist-info/WHEEL
luangpor-0.0.3.dist-info/top_level.txt
luangpor-0.0.3.dist-info/RECORD
